{
    "phrase": [
        {
            "phrase_value": "J'en ai une bonne !"
        },
        
        {
            "phrase_value": "Tu veux une blague ? Tu as de la chance, j'en connais plein, "
        },

        {
            "phrase_value": "J'te préviens, avec celle ci tu vas exploser de rire ! "
        },

        {
            "phrase_value": "Bon t'attends pas à une blague de fou, "
        },

        {
            "phrase_value": "Ahah, celle ci elle est géniale ! "
        },

        {
            "phrase_value": "Et une blague pour la route, "
        },

        {
            "phrase_value": "Mmmh, je réflechis ... Ah oui ! "
        },

        {
            "phrase_value": "Roooh ! Tu peux me laisser tranquile ? Bon je suis gentil, je vais t'en faire une de blague, "
        },

        {
            "phrase_value": "Une blague ? Allez, "
        },

        {
            "phrase_value": "Je savais que tu allais me demander une blague ! "
        },

        {
            "phrase_value": "Une de mes meilleurs blagues : "
        },

        {
            "phrase_value": "Une ptite blague ? Voilà s'en une : "
        },

        {
            "phrase_value": "Uh.. ? Tu veux quoi ? Une blague ? Rhaa j'allais m'endormir ... bon, "
        }

    ]
}